Metadata-Version: 2.1
Name: TextExtract
Version: 1.0.1
Summary: Tesseract Optimize is a optimize version of Tesseract to provide better text recognition.
Home-page: https://github.com/sam4u3/TextExtract
Author: Sayar Mendis
Author-email: sayarmendis26@gmail.com
License: UNKNOWN
Platform: UNKNOWN
Classifier: Development Status :: 4 - Beta
Classifier: Intended Audience :: Developers
Classifier: License :: OSI Approved :: MIT License
Classifier: Natural Language :: English
Classifier: Programming Language :: Python :: 3.6
